rubicon_ml/__init__.py
rubicon_ml/cli.py
rubicon_ml/exceptions.py
rubicon_ml/client/__init__.py
rubicon_ml/client/artifact.py
rubicon_ml/client/base.py
rubicon_ml/client/config.py
rubicon_ml/client/dataframe.py
rubicon_ml/client/experiment.py
rubicon_ml/client/feature.py
rubicon_ml/client/metric.py
rubicon_ml/client/mixin.py
rubicon_ml/client/parameter.py
rubicon_ml/client/project.py
rubicon_ml/client/rubicon.py
rubicon_ml/client/rubicon_json.py
rubicon_ml/client/utils/__init__.py
rubicon_ml/client/utils/exception_handling.py
rubicon_ml/client/utils/tags.py
rubicon_ml/domain/__init__.py
rubicon_ml/domain/artifact.py
rubicon_ml/domain/dataframe.py
rubicon_ml/domain/experiment.py
rubicon_ml/domain/feature.py
rubicon_ml/domain/metric.py
rubicon_ml/domain/mixin.py
rubicon_ml/domain/parameter.py
rubicon_ml/domain/project.py
rubicon_ml/domain/utils/__init__.py
rubicon_ml/domain/utils/training_metadata.py
rubicon_ml/domain/utils/uuid.py
rubicon_ml/intake_rubicon/__init__.py
rubicon_ml/intake_rubicon/base.py
rubicon_ml/intake_rubicon/experiment.py
rubicon_ml/intake_rubicon/publish.py
rubicon_ml/intake_rubicon/viz.py
rubicon_ml/repository/__init__.py
rubicon_ml/repository/base.py
rubicon_ml/repository/local.py
rubicon_ml/repository/memory.py
rubicon_ml/repository/s3.py
rubicon_ml/repository/utils/__init__.py
rubicon_ml/repository/utils/json.py
rubicon_ml/repository/utils/slugify.py
rubicon_ml/schema/__init__.py
rubicon_ml/schema/logger.py
rubicon_ml/schema/registry.py
rubicon_ml/schema/schema/h2o__H2OGeneralizedLinearEstimator.yaml
rubicon_ml/schema/schema/h2o__H2OGenericEstimator.yaml
rubicon_ml/schema/schema/h2o__H2OGradientBoostingEstimator.yaml
rubicon_ml/schema/schema/h2o__H2ORandomForestEstimator.yaml
rubicon_ml/schema/schema/h2o__H2OTargetEncoderEstimator.yaml
rubicon_ml/schema/schema/h2o__H2OXGBoostEstimator.yaml
rubicon_ml/schema/schema/h2o__ModelBase.yaml
rubicon_ml/schema/schema/lightgbm__LGBMClassifier.yaml
rubicon_ml/schema/schema/lightgbm__LGBMModel.yaml
rubicon_ml-0.13.2.dist-info/licenses/LICENSE
rubicon_ml-0.13.2.dist-info/METADATA
rubicon_ml-0.13.2.dist-info/WHEEL
rubicon_ml-0.13.2.dist-info/entry_points.txt
rubicon_ml-0.13.2.dist-info/top_level.txt
rubicon_ml-0.13.2.dist-info/RECORD
