Metadata-Version: 2.4
Name: rubicon-ml
Version: 0.13.2
Summary: AI/ML lifecycle metadata logger with configurable backends
Author: Ryan Soley, Capital One
License: Apache License, Version 2.0
Project-URL: Bug Tracker, https://github.com/capitalone/rubicon-ml/issues
Project-URL: Documentation, https://capitalone.github.io/rubicon-ml/
Project-URL: Source Code, https://github.com/capitalone/rubicon-ml
Classifier: Development Status :: 4 - Beta
Classifier: Intended Audience :: Developers
Classifier: Intended Audience :: Science/Research
Classifier: License :: OSI Approved :: Apache Software License
Classifier: Programming Language :: Python :: 3 :: Only
Classifier: Programming Language :: Python :: 3.10
Classifier: Programming Language :: Python :: 3.11
Classifier: Programming Language :: Python :: 3.12
Classifier: Programming Language :: Python :: 3.13
Classifier: Topic :: Scientific/Engineering
Classifier: Topic :: Scientific/Engineering :: Information Analysis
Classifier: Topic :: Software Development :: Build Tools
Classifier: Topic :: Software Development :: Documentation
Requires-Python: >=3.10.0
License-File: LICENSE
Requires-Dist: click<=8.3.0,>=7.1
Requires-Dist: fsspec<=2025.10.0,>=2021.4.0
Requires-Dist: intake<=2.0.8,>=0.5.2
Requires-Dist: jsonpath-ng<=1.7.0,>=1.5.3
Requires-Dist: numpy<=2.3.4,>=1.22.0
Requires-Dist: pandas<=2.3.3,>=1.0.0
Requires-Dist: pyarrow<=22.0.0,>=14.0.1
Requires-Dist: pyyaml<=6.0.3,>=5.4.0
Requires-Dist: scikit-learn<=1.7.2,>=0.22.0
Provides-Extra: all
Requires-Dist: rubicon-ml[s3,viz]; extra == "all"
Provides-Extra: build
Requires-Dist: build; extra == "build"
Requires-Dist: setuptools; extra == "build"
Requires-Dist: twine; extra == "build"
Requires-Dist: wheel; extra == "build"
Provides-Extra: dev
Requires-Dist: rubicon-ml[build,docs,ops,s3,test,viz]; extra == "dev"
Provides-Extra: docs
Requires-Dist: furo; extra == "docs"
Requires-Dist: ipython; extra == "docs"
Requires-Dist: nbsphinx; extra == "docs"
Requires-Dist: numpydoc; extra == "docs"
Requires-Dist: pandoc; extra == "docs"
Requires-Dist: rubicon-ml[viz]; extra == "docs"
Requires-Dist: sphinx; extra == "docs"
Requires-Dist: sphinx-copybutton; extra == "docs"
Provides-Extra: ops
Requires-Dist: bumpver; extra == "ops"
Requires-Dist: edgetest; extra == "ops"
Requires-Dist: pre-commit; extra == "ops"
Requires-Dist: pyproject-fmt; extra == "ops"
Requires-Dist: ruff; extra == "ops"
Provides-Extra: s3
Requires-Dist: s3fs<=2025.10.0,>=0.4; extra == "s3"
Provides-Extra: test
Requires-Dist: dask[dataframe,distributed]<2025.4.0; extra == "test"
Requires-Dist: h2o; extra == "test"
Requires-Dist: ipykernel; extra == "test"
Requires-Dist: jupyterlab; extra == "test"
Requires-Dist: kaleido==0.2.1; extra == "test"
Requires-Dist: lightgbm; extra == "test"
Requires-Dist: nbconvert; extra == "test"
Requires-Dist: palmerpenguins; extra == "test"
Requires-Dist: pillow; extra == "test"
Requires-Dist: polars<1.0; extra == "test"
Requires-Dist: pytest; extra == "test"
Requires-Dist: pytest-cov; extra == "test"
Requires-Dist: xgboost; extra == "test"
Provides-Extra: ui
Requires-Dist: rubicon-ml[viz]; extra == "ui"
Provides-Extra: viz
Requires-Dist: dash<=2.18.2,>=2.11.0; extra == "viz"
Requires-Dist: dash-bootstrap-components<=1.7.1,>=1.0.0; extra == "viz"
Dynamic: license-file
